{
    "LinkedArraySize": 6,
    "Date": "2017-07-28 14:00:00",
    "TimeWindowLen": "one hour",
    "LinkedArray_1": {
        "nodeSize": 1,
        "AllNodeNameArray": [
            "中新网英文"
        ],
        "node_1": {
            "ID": 605,
            "nodeName": "中新网英文",
            "nodeInfo": {}
        },
        "keywords": [
            "Indian",
            "yoga",
            "teachers",
            "China",
            "enjoy",
            "life",
            "Velusamy",
            "her",
            "Kunming",
            "said"
        ]
    },
    "LinkedArray_2": {
        "nodeSize": 1,
        "AllNodeNameArray": [
            "环球网"
        ],
        "node_1": {
            "ID": 26,
            "nodeName": "环球网",
            "nodeInfo": {}
        },
        "keywords": [
            "uber",
            "腾讯",
            "扩张",
            "滴滴",
            "雪上加霜",
            "Ola",
            "亿美元",
            "外媒"
        ]
    },
    "LinkedArray_3": {
        "nodeSize": 1,
        "AllNodeNameArray": [
            "金融界"
        ],
        "node_1": {
            "ID": 2,
            "nodeName": "金融界",
            "nodeInfo": {}
        },
        "keywords": [
            "降息",
            "通胀",
            "下周",
            "低迷",
            "促使",
            "日期",
            "服务",
            "购买",
            "印度",
            "央行"
        ]
    },
    "LinkedArray_4": {
        "nodeSize": 1,
        "AllNodeNameArray": [
            "TechWeb"
        ],
        "node_1": {
            "ID": 267,
            "nodeName": "TechWeb",
            "nodeInfo": {}
        },
        "keywords": [
            "外媒",
            "Ola",
            "腾讯",
            "亿美元",
            "叫车",
            "投资",
            "资金"
        ]
    },
    "LinkedArray_5": {
        "nodeSize": 1,
        "AllNodeNameArray": [
            "中国政府网"
        ],
        "node_1": {
            "ID": 588,
            "nodeName": "中国政府网",
            "nodeInfo": {}
        },
        "keywords": [
            "killed",
            "over",
            "three",
            "dozen",
            "injured",
            "road",
            "accident",
            "India",
            "north",
            "were"
        ]
    },
    "LinkedArray_6": {
        "nodeSize": 1,
        "AllNodeNameArray": [
            "Global Times"
        ],
        "node_1": {
            "ID": 566,
            "nodeName": "Global Times",
            "nodeInfo": {}
        },
        "keywords": [
            "killed",
            "over",
            "three",
            "dozen",
            "injured",
            "road",
            "accident",
            "India",
            "north",
            "were"
        ]
    }
}