{
    "LinkedArraySize": 6,
    "Date": "2017-07-06 13:00:00",
    "TimeWindowLen": "one hour",
    "LinkedArray_1": {
        "nodeSize": 1,
        "AllNodeNameArray": [
            "空军世界"
        ],
        "node_1": {
            "ID": 222,
            "nodeName": "空军世界",
            "nodeInfo": {}
        },
        "keywords": [
            "联合演习",
            "对峙",
            "印度洋",
            "印齐",
            "美日",
            "边境",
            "军演",
            "联合",
            "印度",
            "航空母舰"
        ]
    },
    "LinkedArray_2": {
        "nodeSize": 1,
        "AllNodeNameArray": [
            "空军世界"
        ],
        "node_1": {
            "ID": 222,
            "nodeName": "空军世界",
            "nodeInfo": {}
        },
        "keywords": [
            "联合演习",
            "对峙",
            "印度洋",
            "印齐",
            "美日",
            "边境",
            "军演",
            "联合",
            "印度",
            "航空母舰"
        ]
    },
    "LinkedArray_3": {
        "nodeSize": 1,
        "AllNodeNameArray": [
            "武器先生"
        ],
        "node_1": {
            "ID": 226,
            "nodeName": "武器先生",
            "nodeInfo": {}
        },
        "keywords": [
            "越境",
            "试射",
            "快速反应",
            "地空导弹",
            "底气",
            "一枚",
            "印度",
            "发射系统"
        ]
    },
    "LinkedArray_4": {
        "nodeSize": 1,
        "AllNodeNameArray": [
            "武器先生"
        ],
        "node_1": {
            "ID": 226,
            "nodeName": "武器先生",
            "nodeInfo": {}
        },
        "keywords": [
            "越境",
            "试射",
            "快速反应",
            "地空导弹",
            "底气",
            "一枚",
            "印度",
            "发射系统"
        ]
    },
    "LinkedArray_5": {
        "nodeSize": 1,
        "AllNodeNameArray": [
            "参考消息网"
        ],
        "node_1": {
            "ID": 31,
            "nodeName": "参考消息网",
            "nodeInfo": {}
        },
        "keywords": [
            "完美无缺",
            "制造商",
            "这款",
            "步枪",
            "拒收",
            "陆军",
            "突击",
            "新德里",
            "测试",
            "印度"
        ]
    },
    "LinkedArray_6": {
        "nodeSize": 1,
        "AllNodeNameArray": [
            "环球网"
        ],
        "node_1": {
            "ID": 26,
            "nodeName": "环球网",
            "nodeInfo": {}
        },
        "keywords": [
            "救济",
            "上半年",
            "印度",
            "对华贸易",
            "商务部",
            "立案",
            "贸易",
            "发起",
            "涉案"
        ]
    }
}