{
    "LinkedArraySize": 10,
    "Date": "2017-07-31 18:00:00",
    "TimeWindowLen": "one hour",
    "LinkedArray_1": {
        "nodeSize": 1,
        "AllNodeNameArray": [
            "中国政府网"
        ],
        "node_1": {
            "ID": 588,
            "nodeName": "中国政府网",
            "nodeInfo": {}
        },
        "keywords": [
            "Indian",
            "markets",
            "higher",
            "close",
            "closed",
            "stocks"
        ]
    },
    "LinkedArray_2": {
        "nodeSize": 5,
        "AllNodeNameArray": [
            "中国日报BBS",
            "火星方阵",
            "铁血讲武堂",
            "铁血讲武堂",
            "Global Times"
        ],
        "node_1": {
            "ID": 560,
            "nodeName": "中国日报BBS",
            "nodeInfo": {}
        },
        "node_2": {
            "ID": 521,
            "nodeName": "火星方阵",
            "nodeInfo": {}
        },
        "node_3": {
            "ID": 300,
            "nodeName": "铁血讲武堂",
            "nodeInfo": {}
        },
        "node_4": {
            "ID": 300,
            "nodeName": "铁血讲武堂",
            "nodeInfo": {}
        },
        "node_5": {
            "ID": 566,
            "nodeName": "Global Times",
            "nodeInfo": {}
        },
        "keywords": [
            "不丹",
            "印度",
            "巴铁",
            "出事",
            "中国",
            "印军",
            "撤军",
            "万全",
            "增兵",
            "关键时刻"
        ]
    },
    "LinkedArray_3": {
        "nodeSize": 1,
        "AllNodeNameArray": [
            "四川日报"
        ],
        "node_1": {
            "ID": 60,
            "nodeName": "四川日报",
            "nodeInfo": {}
        },
        "keywords": [
            "人死于",
            "闪电",
            "雷劈",
            "惨遭",
            "印度",
            "奥里萨邦"
        ]
    },
    "LinkedArray_4": {
        "nodeSize": 4,
        "AllNodeNameArray": [
            "侠客岛",
            "侠客岛",
            "侠客岛",
            "侠客岛"
        ],
        "node_1": {
            "ID": 170,
            "nodeName": "侠客岛",
            "nodeInfo": {}
        },
        "node_2": {
            "ID": 170,
            "nodeName": "侠客岛",
            "nodeInfo": {}
        },
        "node_3": {
            "ID": 170,
            "nodeName": "侠客岛",
            "nodeInfo": {}
        },
        "node_4": {
            "ID": 170,
            "nodeName": "侠客岛",
            "nodeInfo": {}
        },
        "keywords": [
            "解局",
            "完习",
            "来犯之敌",
            "讲话"
        ]
    },
    "LinkedArray_5": {
        "nodeSize": 2,
        "AllNodeNameArray": [
            "海外网",
            "侠客岛"
        ],
        "node_1": {
            "ID": 158,
            "nodeName": "海外网",
            "nodeInfo": {}
        },
        "node_2": {
            "ID": 170,
            "nodeName": "侠客岛",
            "nodeInfo": {}
        },
        "keywords": [
            "领土",
            "台媒",
            "不畏",
            "捍卫",
            "警告",
            "来犯之敌",
            "讲话",
            "印度",
            "印方",
            "洞朗"
        ]
    },
    "LinkedArray_6": {
        "nodeSize": 1,
        "AllNodeNameArray": [
            "侠客岛"
        ],
        "node_1": {
            "ID": 170,
            "nodeName": "侠客岛",
            "nodeInfo": {}
        },
        "keywords": [
            "解局",
            "完习",
            "来犯之敌",
            "讲话"
        ]
    },
    "LinkedArray_7": {
        "nodeSize": 4,
        "AllNodeNameArray": [
            "龙起",
            "龙起",
            "军事帝",
            "军事帝"
        ],
        "node_1": {
            "ID": 578,
            "nodeName": "龙起",
            "nodeInfo": {}
        },
        "node_2": {
            "ID": 578,
            "nodeName": "龙起",
            "nodeInfo": {}
        },
        "node_3": {
            "ID": 550,
            "nodeName": "军事帝",
            "nodeInfo": {}
        },
        "node_4": {
            "ID": 550,
            "nodeName": "军事帝",
            "nodeInfo": {}
        },
        "keywords": [
            "阿琼",
            "LCA",
            "一款",
            "朱日",
            "巴铁",
            "阅兵",
            "不输",
            "潜心",
            "宣告",
            "导弹"
        ]
    },
    "LinkedArray_8": {
        "nodeSize": 1,
        "AllNodeNameArray": [
            "火星方阵"
        ],
        "node_1": {
            "ID": 521,
            "nodeName": "火星方阵",
            "nodeInfo": {}
        },
        "keywords": [
            "不丹",
            "印军",
            "撤军",
            "军队",
            "安抚",
            "印度",
            "洞朗",
            "中国",
            "领土",
            "Bhushan"
        ]
    },
    "LinkedArray_9": {
        "nodeSize": 2,
        "AllNodeNameArray": [
            "铁血讲武堂",
            "铁血讲武堂"
        ],
        "node_1": {
            "ID": 300,
            "nodeName": "铁血讲武堂",
            "nodeInfo": {}
        },
        "node_2": {
            "ID": 300,
            "nodeName": "铁血讲武堂",
            "nodeInfo": {}
        },
        "keywords": [
            "雄文",
            "夜不能寐",
            "血性",
            "挑衅",
            "一篇",
            "战区",
            "八一",
            "英雄",
            "嘲弄",
            "少年"
        ]
    },
    "LinkedArray_10": {
        "nodeSize": 1,
        "AllNodeNameArray": [
            "Global Times"
        ],
        "node_1": {
            "ID": 566,
            "nodeName": "Global Times",
            "nodeInfo": {}
        },
        "keywords": [
            "边界",
            "紧张局势",
            "煽动",
            "民族主义",
            "公民",
            "平静",
            "Doklam",
            "印度",
            "对峙",
            "中国"
        ]
    }
}