{
    "LinkedArraySize": 7,
    "Date": "2017-08-09 16:00:00",
    "TimeWindowLen": "one hour",
    "LinkedArray_1": {
        "nodeSize": 4,
        "AllNodeNameArray": [
            "环球时报",
            "环球时报-环球网",
            "四川日报",
            "环球网"
        ],
        "node_1": {
            "ID": 83,
            "nodeName": "环球时报",
            "nodeInfo": {}
        },
        "node_2": {
            "ID": 86,
            "nodeName": "环球时报-环球网",
            "nodeInfo": {}
        },
        "node_3": {
            "ID": 60,
            "nodeName": "四川日报",
            "nodeInfo": {}
        },
        "node_4": {
            "ID": 26,
            "nodeName": "环球网",
            "nodeInfo": {}
        },
        "keywords": [
            "洞朗",
            "尼泊尔",
            "撤军",
            "对峙",
            "中国",
            "无条件",
            "印度",
            "领土",
            "中印",
            "地区"
        ]
    },
    "LinkedArray_2": {
        "nodeSize": 1,
        "AllNodeNameArray": [
            "环球网"
        ],
        "node_1": {
            "ID": 26,
            "nodeName": "环球网",
            "nodeInfo": {}
        },
        "keywords": [
            "SE",
            "芯片",
            "装载",
            "苹果",
            "iPhone7",
            "扩张",
            "iPhone",
            "苹果公司",
            "手机",
            "处理器"
        ]
    },
    "LinkedArray_3": {
        "nodeSize": 1,
        "AllNodeNameArray": [
            "中新网英文"
        ],
        "node_1": {
            "ID": 605,
            "nodeName": "中新网英文",
            "nodeInfo": {}
        },
        "keywords": [
            "金砖",
            "治理",
            "印度",
            "专家",
            "国家",
            "集团",
            "全球",
            "国际货币基金组织",
            "Kondapalli",
            "帕利"
        ]
    },
    "LinkedArray_4": {
        "nodeSize": 1,
        "AllNodeNameArray": [
            "中新网英文"
        ],
        "node_1": {
            "ID": 605,
            "nodeName": "中新网英文",
            "nodeInfo": {}
        },
        "keywords": [
            "金砖",
            "四国",
            "潜力",
            "国家",
            "贸易",
            "Kondapalli",
            "印度",
            "基础设施",
            "合作",
            "投资"
        ]
    },
    "LinkedArray_5": {
        "nodeSize": 1,
        "AllNodeNameArray": [
            "中国网法文"
        ],
        "node_1": {
            "ID": 558,
            "nodeName": "中国网法文",
            "nodeInfo": {}
        },
        "keywords": [
            "毛里求斯",
            "印度洋",
            "制止",
            "呼吁",
            "国际奥委会",
            "联合国",
            "Lutchmeenaraidoo",
            "地区",
            "研讨会",
            "毒品"
        ]
    },
    "LinkedArray_6": {
        "nodeSize": 1,
        "AllNodeNameArray": [
            "Global Times"
        ],
        "node_1": {
            "ID": 566,
            "nodeName": "Global Times",
            "nodeInfo": {}
        },
        "keywords": [
            "克什米尔",
            "受伤",
            "遇难",
            "落入",
            "峡谷",
            "警方",
            "巴士"
        ]
    },
    "LinkedArray_7": {
        "nodeSize": 1,
        "AllNodeNameArray": [
            "环球网"
        ],
        "node_1": {
            "ID": 26,
            "nodeName": "环球网",
            "nodeInfo": {}
        },
        "keywords": [
            "两套",
            "弹道导弹",
            "防御",
            "巴基斯坦",
            "边境",
            "系统",
            "拦截导弹",
            "DRDO",
            "印方"
        ]
    }
}