{
    "LinkedArraySize": 6,
    "Date": "2017-08-03 23:00:00",
    "TimeWindowLen": "one hour",
    "LinkedArray_1": {
        "nodeSize": 1,
        "AllNodeNameArray": [
            "金融界"
        ],
        "node_1": {
            "ID": 2,
            "nodeName": "金融界",
            "nodeInfo": {}
        },
        "keywords": [
            "撤回",
            "国防部",
            "深夜",
            "发文",
            "边防部队",
            "越界",
            "印方",
            "中国",
            "军队",
            "印度"
        ]
    },
    "LinkedArray_2": {
        "nodeSize": 1,
        "AllNodeNameArray": [
            "国防部"
        ],
        "node_1": {
            "ID": 122,
            "nodeName": "国防部",
            "nodeInfo": {}
        },
        "keywords": [
            "克制",
            "底线",
            "打消",
            "国防部",
            "深夜",
            "边防部队",
            "越界",
            "印方",
            "中国",
            "军队"
        ]
    },
    "LinkedArray_3": {
        "nodeSize": 1,
        "AllNodeNameArray": [
            "国防部"
        ],
        "node_1": {
            "ID": 122,
            "nodeName": "国防部",
            "nodeInfo": {}
        },
        "keywords": [
            "克制",
            "底线",
            "打消",
            "国防部",
            "深夜",
            "边防部队",
            "越界",
            "印方",
            "中国",
            "军队"
        ]
    },
    "LinkedArray_4": {
        "nodeSize": 1,
        "AllNodeNameArray": [
            "国防部网"
        ],
        "node_1": {
            "ID": 712,
            "nodeName": "国防部网",
            "nodeInfo": {}
        },
        "keywords": [
            "越界",
            "边防部队",
            "非法",
            "发表谈话",
            "国防部",
            "中国",
            "在线",
            "印方",
            "ICP",
            "军队"
        ]
    },
    "LinkedArray_5": {
        "nodeSize": 1,
        "AllNodeNameArray": [
            "国际在线"
        ],
        "node_1": {
            "ID": 23,
            "nodeName": "国际在线",
            "nodeInfo": {}
        },
        "keywords": [
            "越界",
            "边防部队",
            "非法",
            "领土",
            "发表谈话",
            "国防部",
            "印方",
            "中国",
            "军队",
            "善意"
        ]
    },
    "LinkedArray_6": {
        "nodeSize": 1,
        "AllNodeNameArray": [
            "国防部"
        ],
        "node_1": {
            "ID": 122,
            "nodeName": "国防部",
            "nodeInfo": {}
        },
        "keywords": [
            "越界",
            "边防部队",
            "非法",
            "发表谈话",
            "国防部",
            "印方",
            "中国",
            "军队",
            "领土",
            "善意"
        ]
    }
}