{
    "LinkedArraySize": 7,
    "Date": "2017-08-22 21:00:00",
    "TimeWindowLen": "one hour",
    "LinkedArray_1": {
        "nodeSize": 1,
        "AllNodeNameArray": [
            "中华网日语"
        ],
        "node_1": {
            "ID": 501,
            "nodeName": "中华网日语",
            "nodeInfo": {}
        },
        "keywords": [
            "落幕",
            "对抗",
            "边界",
            "境内",
            "印度",
            "发言人"
        ]
    },
    "LinkedArray_2": {
        "nodeSize": 1,
        "AllNodeNameArray": [
            "大国博弈"
        ],
        "node_1": {
            "ID": 679,
            "nodeName": "大国博弈",
            "nodeInfo": {}
        },
        "keywords": [
            "狠揍",
            "挑事",
            "我军"
        ]
    },
    "LinkedArray_3": {
        "nodeSize": 1,
        "AllNodeNameArray": [
            "大国博弈"
        ],
        "node_1": {
            "ID": 679,
            "nodeName": "大国博弈",
            "nodeInfo": {}
        },
        "keywords": [
            "狠揍",
            "挑事",
            "我军"
        ]
    },
    "LinkedArray_4": {
        "nodeSize": 3,
        "AllNodeNameArray": [
            "中国青年网",
            "海外网",
            "中国青年网"
        ],
        "node_1": {
            "ID": 220,
            "nodeName": "中国青年网",
            "nodeInfo": {}
        },
        "node_2": {
            "ID": 158,
            "nodeName": "海外网",
            "nodeInfo": {}
        },
        "node_3": {
            "ID": 220,
            "nodeName": "中国青年网",
            "nodeInfo": {}
        },
        "keywords": [
            "罢工",
            "百万",
            "停摆",
            "银行职员",
            "职员",
            "银行",
            "印度",
            "抗议",
            "卢比",
            "多亿"
        ]
    },
    "LinkedArray_5": {
        "nodeSize": 1,
        "AllNodeNameArray": [
            "澎湃新闻网"
        ],
        "node_1": {
            "ID": 81,
            "nodeName": "澎湃新闻网",
            "nodeInfo": {}
        },
        "keywords": [
            "特朗普",
            "暗含",
            "拉拢",
            "南亚",
            "深意",
            "阿富汗",
            "美国",
            "印度",
            "塔利班",
            "巴基斯坦"
        ]
    },
    "LinkedArray_6": {
        "nodeSize": 1,
        "AllNodeNameArray": [
            "澎湃新闻"
        ],
        "node_1": {
            "ID": 79,
            "nodeName": "澎湃新闻",
            "nodeInfo": {}
        },
        "keywords": [
            "特朗普",
            "暗含",
            "深意"
        ]
    },
    "LinkedArray_7": {
        "nodeSize": 1,
        "AllNodeNameArray": [
            "Global Times"
        ],
        "node_1": {
            "ID": 566,
            "nodeName": "Global Times",
            "nodeInfo": {}
        },
        "keywords": [
            "印度",
            "消费市场",
            "低收入",
            "取代",
            "日本",
            "安倍晋三",
            "中国",
            "产品",
            "边界",
            "经济"
        ]
    }
}