{
    "LinkedArraySize": 5,
    "Date": "2017-08-27 19:00:00",
    "TimeWindowLen": "one hour",
    "LinkedArray_1": {
        "nodeSize": 1,
        "AllNodeNameArray": [
            "超级军事迷"
        ],
        "node_1": {
            "ID": 464,
            "nodeName": "超级军事迷",
            "nodeInfo": {}
        },
        "keywords": [
            "高原",
            "试飞",
            "畏惧",
            "中国空军",
            "作战",
            "战斗机",
            "具备",
            "后勤保障",
            "隐身",
            "印度"
        ]
    },
    "LinkedArray_2": {
        "nodeSize": 1,
        "AllNodeNameArray": [
            "超级军事迷"
        ],
        "node_1": {
            "ID": 464,
            "nodeName": "超级军事迷",
            "nodeInfo": {}
        },
        "keywords": [
            "高原",
            "试飞",
            "畏惧",
            "中国空军",
            "作战",
            "战斗机",
            "具备",
            "后勤保障",
            "隐身",
            "印度"
        ]
    },
    "LinkedArray_3": {
        "nodeSize": 1,
        "AllNodeNameArray": [
            "火器营"
        ],
        "node_1": {
            "ID": 436,
            "nodeName": "火器营",
            "nodeInfo": {}
        },
        "keywords": [
            "老师傅",
            "教练机",
            "请来",
            "帮忙",
            "对手",
            "迎来",
            "鹰式",
            "印度",
            "高级",
            "英国"
        ]
    },
    "LinkedArray_4": {
        "nodeSize": 1,
        "AllNodeNameArray": [
            "火器营"
        ],
        "node_1": {
            "ID": 436,
            "nodeName": "火器营",
            "nodeInfo": {}
        },
        "keywords": [
            "老师傅",
            "教练机",
            "请来",
            "帮忙",
            "对手",
            "迎来",
            "鹰式",
            "印度",
            "高级",
            "英国"
        ]
    },
    "LinkedArray_5": {
        "nodeSize": 1,
        "AllNodeNameArray": [
            "看看新闻网"
        ],
        "node_1": {
            "ID": 329,
            "nodeName": "看看新闻网",
            "nodeInfo": {}
        },
        "keywords": [
            "男友",
            "惨遭",
            "抛弃",
            "接生",
            "女孩",
            "未婚先孕",
            "求助",
            "一名",
            "医院",
            "陪护"
        ]
    }
}