{
    "LinkedArraySize": 10,
    "Date": "2017-08-01 17:00:00",
    "TimeWindowLen": "one hour",
    "LinkedArray_1": {
        "nodeSize": 1,
        "AllNodeNameArray": [
            "中国日报BBS"
        ],
        "node_1": {
            "ID": 560,
            "nodeName": "中国日报BBS",
            "nodeInfo": {}
        },
        "keywords": [
            "大陆",
            "冲入",
            "亚洲",
            "可怜"
        ]
    },
    "LinkedArray_2": {
        "nodeSize": 1,
        "AllNodeNameArray": [
            "中国网法文"
        ],
        "node_1": {
            "ID": 558,
            "nodeName": "中国网法文",
            "nodeInfo": {}
        },
        "keywords": [
            "印控",
            "武装",
            "枪战",
            "克什米尔",
            "克什米尔地区",
            "印度"
        ]
    },
    "LinkedArray_3": {
        "nodeSize": 1,
        "AllNodeNameArray": [
            "金融界"
        ],
        "node_1": {
            "ID": 2,
            "nodeName": "金融界",
            "nodeInfo": {}
        },
        "keywords": [
            "KEYone",
            "限量版",
            "全黑",
            "黑莓",
            "约合",
            "用户手册",
            "适配器",
            "手机",
            "4174.95"
        ]
    },
    "LinkedArray_4": {
        "nodeSize": 1,
        "AllNodeNameArray": [
            "新华网"
        ],
        "node_1": {
            "ID": 69,
            "nodeName": "新华网",
            "nodeInfo": {}
        },
        "keywords": [
            "旗杆",
            "怪风大",
            "光杆",
            "沦落",
            "国旗",
            "这根",
            "印度",
            "英尺",
            "阿姆利",
            "爱国主义"
        ]
    },
    "LinkedArray_5": {
        "nodeSize": 1,
        "AllNodeNameArray": [
            "金融界"
        ],
        "node_1": {
            "ID": 2,
            "nodeName": "金融界",
            "nodeInfo": {}
        },
        "keywords": [
            "电商",
            "软银",
            "亿美元",
            "印度",
            "第一",
            "Flipkart",
            "知情",
            "落到"
        ]
    },
    "LinkedArray_6": {
        "nodeSize": 4,
        "AllNodeNameArray": [
            "中新网",
            "金融界",
            "中国新闻网",
            "中国新闻网"
        ],
        "node_1": {
            "ID": 155,
            "nodeName": "中新网",
            "nodeInfo": {}
        },
        "node_2": {
            "ID": 2,
            "nodeName": "金融界",
            "nodeInfo": {}
        },
        "node_3": {
            "ID": 41,
            "nodeName": "中国新闻网",
            "nodeInfo": {}
        },
        "node_4": {
            "ID": 41,
            "nodeName": "中国新闻网",
            "nodeInfo": {}
        },
        "keywords": [
            "奥里萨邦",
            "雷击",
            "丧生",
            "印度",
            "丧命",
            "致死",
            "季风",
            "自然灾害",
            "医药",
            "雷雨云"
        ]
    },
    "LinkedArray_7": {
        "nodeSize": 3,
        "AllNodeNameArray": [
            "新华网",
            "新华网",
            "新华社"
        ],
        "node_1": {
            "ID": 69,
            "nodeName": "新华网",
            "nodeInfo": {}
        },
        "node_2": {
            "ID": 69,
            "nodeName": "新华网",
            "nodeInfo": {}
        },
        "node_3": {
            "ID": 4,
            "nodeName": "新华社",
            "nodeInfo": {}
        },
        "keywords": [
            "古吉拉特邦",
            "洪灾",
            "人数",
            "死亡",
            "伯纳斯",
            "印度",
            "卢比",
            "洪水",
            "灾情",
            "甘塔县"
        ]
    },
    "LinkedArray_8": {
        "nodeSize": 2,
        "AllNodeNameArray": [
            "利刃军事",
            "利刃军事"
        ],
        "node_1": {
            "ID": 456,
            "nodeName": "利刃军事",
            "nodeInfo": {}
        },
        "node_2": {
            "ID": 456,
            "nodeName": "利刃军事",
            "nodeInfo": {}
        },
        "keywords": [
            "运兵",
            "隧道",
            "最新动向",
            "南坡",
            "喜马拉雅山",
            "炸弹",
            "印度",
            "武器",
            "钢筋",
            "目标"
        ]
    },
    "LinkedArray_9": {
        "nodeSize": 1,
        "AllNodeNameArray": [
            "凤凰国际iMarkets"
        ],
        "node_1": {
            "ID": 18,
            "nodeName": "凤凰国际iMarkets",
            "nodeInfo": {}
        },
        "keywords": [
            "复星",
            "印度",
            "收购案",
            "回应",
            "通知",
            "内政部",
            "Gland",
            "Pharma",
            "投资",
            "医药"
        ]
    },
    "LinkedArray_10": {
        "nodeSize": 2,
        "AllNodeNameArray": [
            "龙起",
            "龙起"
        ],
        "node_1": {
            "ID": 578,
            "nodeName": "龙起",
            "nodeInfo": {}
        },
        "node_2": {
            "ID": 578,
            "nodeName": "龙起",
            "nodeInfo": {}
        },
        "keywords": [
            "全民投票",
            "巴铁",
            "亿买",
            "狂潮",
            "命名",
            "名字",
            "武器",
            "潜艇",
            "巴基斯坦",
            "印巴"
        ]
    }
}