{
    "LinkedArraySize": 5,
    "Date": "2017-08-05 23:00:00",
    "TimeWindowLen": "one hour",
    "LinkedArray_1": {
        "nodeSize": 1,
        "AllNodeNameArray": [
            "中国日报BBS"
        ],
        "node_1": {
            "ID": 560,
            "nodeName": "中国日报BBS",
            "nodeInfo": {}
        },
        "keywords": [
            "印度",
            "精神药物",
            "庇护",
            "服用",
            "中国",
            "忘记",
            "正确"
        ]
    },
    "LinkedArray_2": {
        "nodeSize": 1,
        "AllNodeNameArray": [
            "中国日报BBS"
        ],
        "node_1": {
            "ID": 560,
            "nodeName": "中国日报BBS",
            "nodeInfo": {}
        },
        "keywords": [
            "印度",
            "肮脏",
            "历史",
            "seneA",
            "中国",
            "污染",
            "干净",
            "zits"
        ]
    },
    "LinkedArray_3": {
        "nodeSize": 1,
        "AllNodeNameArray": [
            "中国日报BBS"
        ],
        "node_1": {
            "ID": 560,
            "nodeName": "中国日报BBS",
            "nodeInfo": {}
        },
        "keywords": [
            "印度",
            "庇护",
            "冷床",
            "精神药物",
            "中国"
        ]
    },
    "LinkedArray_4": {
        "nodeSize": 1,
        "AllNodeNameArray": [
            "大众网"
        ],
        "node_1": {
            "ID": 350,
            "nodeName": "大众网",
            "nodeInfo": {}
        },
        "keywords": [
            "洞朗",
            "人民日报",
            "莫迪未",
            "发声",
            "总理",
            "莫迪",
            "对话",
            "冲突",
            "印度",
            "许可证"
        ]
    },
    "LinkedArray_5": {
        "nodeSize": 1,
        "AllNodeNameArray": [
            "人民日报客户端"
        ],
        "node_1": {
            "ID": 412,
            "nodeName": "人民日报客户端",
            "nodeInfo": {}
        },
        "keywords": [
            "洞朗",
            "莫迪未",
            "发声",
            "人民日报",
            "莫迪",
            "印度"
        ]
    }
}